dbcut/__init__.py
dbcut/compiler.py
dbcut/configuration.py
dbcut/database.py
dbcut/exceptions.py
dbcut/generated_models.py
dbcut/models.py
dbcut/parser.py
dbcut/query.py
dbcut/serializer.py
dbcut/session.py
dbcut/sqlalchemy_utils.py
dbcut/utils.py
dbcut/cli/__init__.py
dbcut/cli/context.py
dbcut/cli/main.py
dbcut/cli/operations.py
dbcut/cli/commands/__init__.py
dbcut/cli/commands/cmd_clear.py
dbcut/cli/commands/cmd_dumpjson.py
dbcut/cli/commands/cmd_dumpsql.py
dbcut/cli/commands/cmd_flush.py
dbcut/cli/commands/cmd_inspect.py
dbcut/cli/commands/cmd_load.py
dbcut/cli/commands/cmd_purgecache.py
dbcut/contrib/__init__.py
dbcut/contrib/record.py
tests/__init__.py
tests/test_cli.py
tests/test_utils.py
dbcut-0.6.0.dist-info/LICENSE
dbcut-0.6.0.dist-info/METADATA
dbcut-0.6.0.dist-info/WHEEL
dbcut-0.6.0.dist-info/entry_points.txt
dbcut-0.6.0.dist-info/top_level.txt
dbcut-0.6.0.dist-info/RECORD
