Metadata-Version: 2.1
Name: dbcut
Version: 0.6.0
Summary: Extract a lightweight subset of your relational production database for development and testing purpose.
Home-page: https://github.com/itsolutionsfactory/dbcut
Author: Salem Harrache
Author-email: dev@salem.harrache.info
License: MIT license
Keywords: dbcut
Platform: UNKNOWN
Classifier: Development Status :: 2 - Pre-Alpha
Classifier: Intended Audience :: Developers
Classifier: License :: OSI Approved :: MIT License
Classifier: Natural Language :: English
Classifier: Programming Language :: Python :: 3.6
Classifier: Programming Language :: Python :: 3.7
Classifier: Programming Language :: Python :: 3.8
Classifier: Programming Language :: Python :: 3.9
Requires-Python: >=3.6
Requires-Dist: Click
Requires-Dist: SQLAlchemy
Requires-Dist: mlalchemy
Requires-Dist: pptree
Requires-Dist: python-dotenv
Requires-Dist: tabulate
Requires-Dist: tqdm
Provides-Extra: dev
Requires-Dist: bumpversion ; extra == 'dev'
Requires-Dist: flake8 ; extra == 'dev'
Requires-Dist: jedi ; extra == 'dev'
Requires-Dist: pdbpp ; extra == 'dev'
Requires-Dist: twine ; extra == 'dev'
Requires-Dist: wheel ; extra == 'dev'
Requires-Dist: jinja2 ; extra == 'dev'
Requires-Dist: pyyaml ; extra == 'dev'
Requires-Dist: black ; extra == 'dev'
Requires-Dist: isort ; extra == 'dev'
Provides-Extra: fastjson
Provides-Extra: mysql
Requires-Dist: mysqlclient ; extra == 'mysql'
Provides-Extra: postgresql
Requires-Dist: psycopg2 ; extra == 'postgresql'
Provides-Extra: profiler
Requires-Dist: sqlalchemy-easy-profile ; extra == 'profiler'
Requires-Dist: sqlparse ; extra == 'profiler'
Provides-Extra: test
Requires-Dist: pytest (==6.0.1) ; extra == 'test'
Requires-Dist: pytest-cov (==2.10.0) ; extra == 'test'
Requires-Dist: pytest-sugar (==0.9.4) ; extra == 'test'
Requires-Dist: coverage (==5.2.1) ; extra == 'test'
